lyft_dataset_sdk/__init__.py
lyft_dataset_sdk/lyftdataset.py
lyft_dataset_sdk/eval/__init__.py
lyft_dataset_sdk/eval/detection/__init__.py
lyft_dataset_sdk/eval/detection/mAP_evaluation.py
lyft_dataset_sdk/utils/__init__.py
lyft_dataset_sdk/utils/data_classes.py
lyft_dataset_sdk/utils/geometry_utils.py
lyft_dataset_sdk/utils/map_mask.py
lyft_dataset_sdk-0.0.8.dist-info/METADATA
lyft_dataset_sdk-0.0.8.dist-info/WHEEL
lyft_dataset_sdk-0.0.8.dist-info/top_level.txt
lyft_dataset_sdk-0.0.8.dist-info/RECORD
