Metadata-Version: 2.1
Name: lyft-dataset-sdk
Version: 0.0.8
Summary: SDK for Lyft dataset.
Home-page: https://github.com/lyft/nuscenes-devkit
Author: Vladimir Iglovikov
License: Attribution-NonCommercial-ShareAlike 4.0 International (CC BY-NC-SA 4.0)
Platform: UNKNOWN
Classifier: Intended Audience :: Developers
Classifier: Intended Audience :: Science/Research
Classifier: Operating System :: OS Independent
Classifier: Programming Language :: Python
Classifier: Programming Language :: Python :: 3
Classifier: Topic :: Software Development :: Libraries
Classifier: Topic :: Software Development :: Libraries :: Python Modules
Requires-Dist: flake8
Requires-Dist: numpy (>=1.14.5)
Requires-Dist: opencv-python (>=3.4.2.17)
Requires-Dist: Pillow (>=5.2.0)
Requires-Dist: pyquaternion (>=0.9.5)
Requires-Dist: scikit-learn (>=0.19.2)
Requires-Dist: tqdm (>=4.25.0)
Requires-Dist: scipy (>=1.1.0)
Requires-Dist: cachetools (>=3.1.0)
Requires-Dist: Shapely (>=1.6.4.post2)
Requires-Dist: fire
Requires-Dist: pytest
Requires-Dist: black
Requires-Dist: matplotlib
Requires-Dist: pandas
Requires-Dist: plotly
Provides-Extra: test
Requires-Dist: pytest ; extra == 'test'
